{
    "Ar36": {
        "error": 0.00017309670345806282,
        "error_type": "SEM",
        "filter_outliers_dict": {
            "filter_outliers": true,
            "iterations": 1,
            "std_devs": 2,
            "use_iqr_filtering": false,
            "use_standard_deviation_filtering": false
        },
        "fit": "Parabolic",
        "fn": 325,
        "include_baseline_error": true,
        "n": 340,
        "outlier_excluded": [
            64,
            192,
            322,
            197,
            295,
            234,
            204,
            301,
            238,
            177,
            211,
            212,
            307,
            310,
            318
        ],
        "reviewed": true,
        "user_excluded": [],
        "value": 0.0023887009190733622
    },
    "Ar37": {
        "error": 0.013798357351383716,
        "error_type": "SEM",
        "filter_outliers_dict": {
            "filter_outliers": true,
            "iterations": 1,
            "std_devs": 2,
            "use_iqr_filtering": false,
            "use_standard_deviation_filtering": false
        },
        "fit": "Linear",
        "fn": 322,
        "include_baseline_error": true,
        "n": 340,
        "outlier_excluded": [
            0,
            1,
            96,
            130,
            131,
            5,
            230,
            263,
            280,
            328,
            299,
            80,
            112,
            181,
            120,
            153,
            155,
            60
        ],
        "reviewed": true,
        "user_excluded": [],
        "value": 0.137836486471777
    },
    "Ar38": {
        "error": 0.004957857729188431,
        "error_type": "SEM",
        "filter_outliers_dict": {
            "filter_outliers": true,
            "iterations": 1,
            "std_devs": 2,
            "use_iqr_filtering": false,
            "use_standard_deviation_filtering": false
        },
        "fit": "Linear",
        "fn": 321,
        "include_baseline_error": true,
        "n": 340,
        "outlier_excluded": [
            129,
            6,
            262,
            285,
            40,
            300,
            184,
            186,
            64,
            194,
            69,
            201,
            215,
            90,
            96,
            231,
            104,
            232,
            242
        ],
        "reviewed": true,
        "user_excluded": [],
        "value": 0.09436196064202197
    },
    "Ar39": {
        "error": 0.013600006775048353,
        "error_type": "SEM",
        "filter_outliers_dict": {
            "filter_outliers": true,
            "iterations": 1,
            "std_devs": 2,
            "use_iqr_filtering": false,
            "use_standard_deviation_filtering": false
        },
        "fit": "Parabolic",
        "fn": 324,
        "include_baseline_error": true,
        "n": 340,
        "outlier_excluded": [
            289,
            196,
            260,
            324,
            264,
            140,
            209,
            274,
            307,
            21,
            214,
            311,
            312,
            91,
            127,
            159
        ],
        "reviewed": true,
        "user_excluded": [],
        "value": -0.029417396817134935
    },
    "Ar40": {
        "error": 0.02590721236040629,
        "error_type": "SEM",
        "filter_outliers_dict": {
            "filter_outliers": true,
            "iterations": 1,
            "std_devs": 2,
            "use_iqr_filtering": false,
            "use_standard_deviation_filtering": false
        },
        "fit": "Parabolic",
        "fn": 326,
        "include_baseline_error": true,
        "n": 340,
        "outlier_excluded": [
            65,
            99,
            325,
            72,
            247,
            170,
            44,
            13,
            334,
            114,
            85,
            87,
            219,
            92
        ],
        "reviewed": true,
        "user_excluded": [],
        "value": -0.08453423532893914
    }
}